LICENSE.txt
MANIFEST.in
README.md
pyproject.toml
setup.cfg
src/socket_oneline/__init__.py
src/socket_oneline/build_info.py
src/socket_oneline/constants.py
src/socket_oneline/constants_version.py
src/socket_oneline/oneline_client.py
src/socket_oneline/oneline_server.py
src/socket_oneline.egg-info/PKG-INFO
src/socket_oneline.egg-info/SOURCES.txt
src/socket_oneline.egg-info/dependency_links.txt
src/socket_oneline.egg-info/requires.txt
src/socket_oneline.egg-info/top_level.txt