Metadata-Version: 2.4
Name: socket-oneline
Version: 1.0.0
Summary: server and client for simple, one line communication protocol
Author-email: "J. Arrizza" <cppgent0@gmail.com>
Maintainer-email: "J. Arrizza" <cppgent0@gmail.com>
License-Expression: MIT
Project-URL: Website, https://arrizza.com/python-socket-oneline
Project-URL: Source, https://bitbucket.org/arrizza-public/socket-oneline/src/master
Project-URL: Download, https://bitbucket.org/arrizza-public/socket-oneline/get/master.zip
Keywords: socket,client server,simple
Classifier: Development Status :: 4 - Beta
Classifier: Environment :: Console
Classifier: Topic :: Utilities
Classifier: Intended Audience :: Developers
Classifier: Programming Language :: Python :: 3.10
Classifier: Programming Language :: Python :: 3.12
Requires-Python: >=3.9
License-File: LICENSE.txt
Requires-Dist: falcon-logger
Dynamic: license-file
